Changelog.md
LICENSE
MANIFEST.in
README.md
setup.cfg
setup.py
examples/MALLET_topic_modelling.ipynb
examples/classify_regions_using_features.ipynb
examples/create_a_full_set_of_meta_analysis_images.py
examples/create_a_new_dataset_and_load_features.py
examples/decode_images.py
examples/download_database_and_abstracts.ipynb
examples/identify_regions_coactivated_with_ROI.ipynb
examples/neurosynth_demo.ipynb
examples/neurosynth_demo.py
neurosynth/__init__.py
neurosynth/utils.py
neurosynth/version.py
neurosynth.egg-info/PKG-INFO
neurosynth.egg-info/SOURCES.txt
neurosynth.egg-info/dependency_links.txt
neurosynth.egg-info/requires.txt
neurosynth.egg-info/top_level.txt
neurosynth/__pycache__/__init__.cpython-36.pyc
neurosynth/__pycache__/utils.cpython-36.pyc
neurosynth/__pycache__/version.cpython-36.pyc
neurosynth/analysis/__init__.py
neurosynth/analysis/classify.py
neurosynth/analysis/cluster.py
neurosynth/analysis/decode.py
neurosynth/analysis/meta.py
neurosynth/analysis/network.py
neurosynth/analysis/plotutils.py
neurosynth/analysis/reduce.py
neurosynth/analysis/stats.py
neurosynth/analysis/__pycache__/__init__.cpython-36.pyc
neurosynth/analysis/__pycache__/classify.cpython-36.pyc
neurosynth/analysis/__pycache__/cluster.cpython-36.pyc
neurosynth/analysis/__pycache__/decode.cpython-36.pyc
neurosynth/analysis/__pycache__/meta.cpython-36.pyc
neurosynth/analysis/__pycache__/network.cpython-36.pyc
neurosynth/analysis/__pycache__/reduce.cpython-36.pyc
neurosynth/analysis/__pycache__/stats.cpython-36.pyc
neurosynth/base/__init__.py
neurosynth/base/dataset.py
neurosynth/base/imageutils.py
neurosynth/base/lexparser.py
neurosynth/base/lextab.py
neurosynth/base/mask.py
neurosynth/base/parser.out
neurosynth/base/parsetab.py
neurosynth/base/transformations.py
neurosynth/base/__pycache__/__init__.cpython-36.pyc
neurosynth/base/__pycache__/dataset.cpython-36.pyc
neurosynth/base/__pycache__/imageutils.cpython-36.pyc
neurosynth/base/__pycache__/lexparser.cpython-36.pyc
neurosynth/base/__pycache__/mask.cpython-36.pyc
neurosynth/base/__pycache__/parsetab.cpython-36.pyc
neurosynth/base/__pycache__/transformations.cpython-36.pyc
