Metadata-Version: 2.1
Name: neurosynth
Version: 0.3.7
Summary: Large-scale synthesis of functional neuroimaging data
Home-page: http://github.com/neurosynth/neurosynth
Maintainer: Tal Yarkoni
Maintainer-email: tyarkoni@gmail.com
License: UNKNOWN
Download-URL: https://github.com/neurosynth/neurosynth/tarball/0.3.7
Platform: UNKNOWN
Provides-Extra: test
